[
   [
      {
         "png":"assets/huntress/idle.png",
         "time":0.1,
         "view":{
            "x":55,
            "y":53,
            "width":40,
            "height":50
         }
      },
      {
         "png":"assets/huntress/idle.png",
         "time":0.2,
         "view":{
            "x":205,
            "y":53,
            "width":40,
            "height":50
         }
      },
      {
         "png":"assets/huntress/idle.png",
         "time":0.3,
         "view":{
            "x":355,
            "y":53,
            "width":40,
            "height":50
         }
      },
      {
         "png":"assets/huntress/idle.png",
         "time":0.4,
         "view":{
            "x":505,
            "y":53,
            "width":40,
            "height":50
         }
      },
      {
         "png":"assets/huntress/idle.png",
         "time":0.5,
         "view":{
            "x":655,
            "y":53,
            "width":40,
            "height":50
         }
      },
      {
         "png":"assets/huntress/idle.png",
         "time":0.6,
         "view":{
            "x":805,
            "y":53,
            "width":40,
            "height":50
         }
      },
      {
         "png":"assets/huntress/idle.png",
         "time":0.7,
         "view":{
            "x":955,
            "y":53,
            "width":40,
            "height":50
         }
      },
      {
         "png":"assets/huntress/idle.png",
         "time":0.8,
         "view":{
            "x":1105,
            "y":53,
            "width":40,
            "height":50
         }
      }
   ],
   [
      {
         "png":"assets/huntress/run.png",
         "time":0.1,
         "view":{
            "x":55,
            "y":53,
            "width":40,
            "height":50
         }
      },
      {
         "png":"assets/huntress/run.png",
         "time":0.2,
         "view":{
            "x":205,
            "y":53,
            "width":40,
            "height":50
         }
      },
      {
         "png":"assets/huntress/run.png",
         "time":0.3,
         "view":{
            "x":355,
            "y":53,
            "width":40,
            "height":50
         }
      },
      {
         "png":"assets/huntress/run.png",
         "time":0.4,
         "view":{
            "x":505,
            "y":53,
            "width":40,
            "height":50
         }
      },
      {
         "png":"assets/huntress/run.png",
         "time":0.5,
         "view":{
            "x":655,
            "y":53,
            "width":40,
            "height":50
         }
      },
      {
         "png":"assets/huntress/run.png",
         "time":0.6,
         "view":{
            "x":805,
            "y":53,
            "width":40,
            "height":50
         }
      },
      {
         "png":"assets/huntress/run.png",
         "time":0.7,
         "view":{
            "x":955,
            "y":53,
            "width":40,
            "height":50
         }
      },
      {
         "png":"assets/huntress/run.png",
         "time":0.8,
         "view":{
            "x":1105,
            "y":53,
            "width":40,
            "height":50
         }
      }
   ],
   [
      {
         "png":"assets/huntress/attack2.png",
         "time":0.2,
         "view":{
            "x":55,
            "y":53,
            "width":40,
            "height":50
         }
      },
      {
         "png":"assets/huntress/attack2.png",
         "time":0.3,
         "view":{
            "x":205,
            "y":53,
            "width":40,
            "height":50
         }
      },
      {
         "png":"assets/huntress/attack2.png",
         "time":0.35,
         "view":{
            "x":355,
            "y":53,
            "width":40,
            "height":50
         }
      },
      {
         "png":"assets/huntress/attack2.png",
         "time":0.4,
         "view":{
            "x":505,
            "y":53,
            "width":40,
            "height":50
         }
      },
      {
         "png":"assets/huntress/attack2.png",
         "time":0.45,
         "view":{
            "x":655,
            "y":53,
            "width":40,
            "height":50
         }
      }
   ]
]